sii/__init__.py
sii/resource.py
sii/server.py
sii/utils.py
sii/models/__init__.py
sii/models/basic_models.py
sii/models/invoices_deregister.py
sii/models/invoices_record.py
sii-3.0.0.dist-info/METADATA
sii-3.0.0.dist-info/WHEEL
sii-3.0.0.dist-info/top_level.txt
sii-3.0.0.dist-info/RECORD
