Metadata-Version: 2.1
Name: sii
Version: 3.0.0
Summary: Librería de Suministro Inmediato de Información
Home-page: http://www.gisce.net
Author: GISCE-TI, S.L.
Author-email: devel@gisce.net
License: General Public Licence 2
Platform: UNKNOWN
Classifier: Programming Language :: Python :: 2.7
Classifier: Programming Language :: Python :: 3.6
Provides: sii
Requires-Dist: marshmallow (<3.0.0,>=2.13.5)
Requires-Dist: zeep
Requires-Dist: unidecode
Requires-Dist: python-stdnum
